setup.py
django_timedeltatemplatefilter.egg-info/PKG-INFO
django_timedeltatemplatefilter.egg-info/SOURCES.txt
django_timedeltatemplatefilter.egg-info/dependency_links.txt
django_timedeltatemplatefilter.egg-info/top_level.txt
timedeltatemplatefilter/__init__.py
timedeltatemplatefilter/models.py
timedeltatemplatefilter/views.py
timedeltatemplatefilter/templatetags/__init__.py
timedeltatemplatefilter/templatetags/timedelta_filter.py
timedeltatemplatefilter/tests/__init__.py
timedeltatemplatefilter/tests/runtests.py
timedeltatemplatefilter/tests/tests.py