Metadata-Version: 1.1
Name: django-timedeltatemplatefilter
Version: 0.1.2
Summary: Format timedelta values nicely in your Django templates.
Home-page: http://packages.python.org/django_timedeltatemplatefilter
Author: Fran Hrzenjak
Author-email: frnhr@changeset.hr
License: The Unlicense
Keywords: django timedelta template filter
Platform: UNKNOWN
Classifier: Development Status :: 4 - Beta
Classifier: Topic :: Software Development :: User Interfaces
Classifier: Topic :: Utilities
Classifier: Framework :: Django
Classifier: License :: Public Domain
